{"response":{"legislator":{"@attributes":{"cid":"N00001692","firstlast":"Eleanor Holmes Norton","lastname":"NORTON","party":"D","office":"DC00","gender":"F","first_elected":"1990","exit_code":"0","comments":"","phone":"202-225-8050","fax":"202-225-3002","website":"http:\/\/norton.house.gov","webform":"https:\/\/norton.house.gov\/contact\/email-me","congress_office":"2136 Rayburn House Office Building","bioguide_id":"N000147","votesmart_id":"775","feccandid":"H0DC00058","twitter_id":"EleanorNorton","youtube_url":"http:\/\/youtube.com\/EleanorHNorton","facebook_id":"pages\/foo\/61731840657","birthdate":"1937-06-13"}}}}